src/ram.sv
// jeden modul RAM z paramterami.

module ram#(
    parameter ADDR_WIDTH = 5,
    parameter DATA_WIDTH = 16
)
(
    input wire clk,
    input wire [ADDR_WIDTH-1:0] adres,
    input wire [DATA_WIDTH-1:0] data,
    input wire wr,
    output logic [DATA_WIDTH-1:0] data_out
);

logic [DATA_WIDTH-1:0] pamiec_RAM [0:(1<<ADDR_WIDTH)-1];

always_ff @( posedge clk ) begin : Ram
    if(wr) pamiec_RAM[adres] <= data;
    data_out <= pamiec_RAM[adres];
end

//assign data_out = pamiec_RAM[adres];

endmodule

src/tb/ram_tb.sv
`timescale 1ns/1ps

////////////////////////////////////////////////////////////////////////
//   cd src\tb
//   iverilog -g2012 -o ram_tb.vvp ../ram.sv ram_tb.sv
//   vvp ram_tb.vvp
//   gtkwave ram_tb.vcd
///////////////////////////////////////////////////////////////////////


module ram_tb;

    localparam adres_W = 5;
    localparam data_W = 16;
    // sygnały
    logic clk;
    logic wr_mem;
    logic [adres_W-1:0] adres;
    logic [data_W-1:0] dane;
    logic [data_W-1:0] out;

    // instancja modułu
    ram  #(
        .ADDR_WIDTH(adres_W),
        .DATA_WIDTH(data_W)
    ) DUT (
        .clk(clk),
        .wr(wr_mem),
        .adres(adres),
        .data(dane),
        .data_out(out)
    );

    initial clk = 1;
    always #5 clk = ~clk;

    initial begin
        wr_mem = 0;
        adres  = 0;
        dane   = 0;
        #10;

        //@(posedge clk);
        wr_mem = 1;
        adres  = 8'd0;
        dane   = 8'hAA;
        #10;
        //@(posedge clk);
        wr_mem = 0;

        #10;
        //@(posedge clk);
        wr_mem = 1;
        adres  = 8'd1;
        dane   = 8'h55;
        #10;//@(posedge clk);
        wr_mem = 0;

        #10;//@(posedge clk);
        wr_mem = 1;
        adres  = 8'd10;
        dane   = 8'hCC;
        #10;//@(posedge clk);
        wr_mem = 0;

        #10;//@(posedge clk);
        adres = 8'd0;

        #10;//@(posedge clk);
        adres = 8'd1;

        #10;//@(posedge clk);
        adres = 8'd10;

        #10;//@(posedge clk);
        adres = 8'd2;

        #20;
        wr_mem = 1;
        adres  = 8'd15;
        dane   = 8'hAA;
        #10;
        adres  = 8'd16;
        dane   = 8'hAB;
        #10;
        adres  = 8'd17;
        dane   = 8'hAC;
        #10;
        wr_mem = 0;

        #20;
        adres = 8'd15;
        #10;
        adres  = 8'd16;
        #10;
        adres  = 8'd17;

        #300;
        $finish;
    end

    initial begin
        $dumpfile("ram_tb.vcd");
        $dumpvars(0, ram_tb);
    end


endmodule

src/tb/ram_tb.vcd
$date
	Fri Jan 02 02:27:08 2026
$end
$version
	Icarus Verilog
$end
$timescale
	1ps
$end
$scope module ram_tb $end
$var wire 16 ! out [15:0] $end
$var parameter 32 " adres_W $end
$var parameter 32 # data_W $end
$var reg 5 $ adres [4:0] $end
$var reg 1 % clk $end
$var reg 16 & dane [15:0] $end
$var reg 1 ' wr_mem $end
$scope module DUT $end
$var wire 5 ( adres [4:0] $end
$var wire 1 % clk $end
$var wire 16 ) data [15:0] $end
$var wire 1 ' wr $end
$var parameter 32 * ADDR_WIDTH $end
$var parameter 32 + DATA_WIDTH $end
$var reg 16 , data_out [15:0] $end
$scope begin Ram $end
$upscope $end
$upscope $end
$upscope $end
$enddefinitions $end
$comment Show the parameter values. $end
$dumpall
b10000 +
b101 *
b10000 #
b101 "
$end
#0
$dumpvars
bx ,
b0 )
b0 (
0'
b0 &
1%
b0 $
bx !
$end
#5000
0%
#10000
1%
b10101010 &
b10101010 )
1'
#15000
0%
#20000
b10101010 !
b10101010 ,
1%
0'
#25000
0%
#30000
1%
b1010101 &
b1010101 )
b1 $
b1 (
1'
#35000
0%
#40000
b1010101 !
b1010101 ,
1%
0'
#45000
0%
#50000
1%
b11001100 &
b11001100 )
b1010 $
b1010 (
1'
#55000
0%
#60000
b11001100 !
b11001100 ,
1%
0'
#65000
0%
#70000
b10101010 !
b10101010 ,
1%
b0 $
b0 (
#75000
0%
#80000
b1010101 !
b1010101 ,
1%
b1 $
b1 (
#85000
0%
#90000
b11001100 !
b11001100 ,
1%
b1010 $
b1010 (
#95000
0%
#100000
bx !
bx ,
1%
b10 $
b10 (
#105000
0%
#110000
1%
#115000
0%
#120000
1%
b10101010 &
b10101010 )
b1111 $
b1111 (
1'
#125000
0%
#130000
1%
b10101011 &
b10101011 )
b10000 $
b10000 (
#135000
0%
#140000
1%
b10101100 &
b10101100 )
b10001 $
b10001 (
#145000
0%
#150000
b10101100 !
b10101100 ,
1%
0'
#155000
0%
#160000
1%
#165000
0%
#170000
b10101010 !
b10101010 ,
1%
b1111 $
b1111 (
#175000
0%
#180000
b10101011 !
b10101011 ,
1%
b10000 $
b10000 (
#185000
0%
#190000
b10101100 !
b10101100 ,
1%
b10001 $
b10001 (
