src/ram.sv
// jeden modul RAM z paramterami.

module ram#(
    parameter ADDR_WIDTH = 5,
    parameter DATA_WIDTH = 16
)
(
    input wire clk,
    input wire [ADDR_WIDTH-1:0] adres,
    input wire [DATA_WIDTH-1:0] data,
    input wire wr,
    output logic [DATA_WIDTH-1:0] data_out
);

logic [DATA_WIDTH-1:0] pamiec_RAM [0:(1<<ADDR_WIDTH)-1];

always_ff @( posedge clk ) begin : Ram
    if(wr) pamiec_RAM[adres] <= data;
    data_out <= pamiec_RAM[adres];
end

//assign data_out = pamiec_RAM[adres];

endmodule

src/tb/ram_tb.sv
`timescale 1ns/1ps

////////////////////////////////////////////////////////////////////////
//   cd src\tb
//   iverilog -g2012 -o ram_tb.vvp ../ram.sv ram_tb.sv
//   vvp ram_tb.vvp
//   gtkwave ram_tb.vcd
///////////////////////////////////////////////////////////////////////


module ram_tb;

    localparam adres_W = 5;
    localparam data_W = 16;
    // sygnały
    logic clk;
    logic wr_mem;
    logic [adres_W-1:0] adres;
    logic [data_W-1:0] dane;
    logic [data_W-1:0] out;

    // instancja modułu
    ram  #(
        .ADDR_WIDTH(adres_W),
        .DATA_WIDTH(data_W)
    ) DUT (
        .clk(clk),
        .wr(wr_mem),
        .adres(adres),
        .data(dane),
        .data_out(out)
    );

    initial clk = 1;
    always #5 clk = ~clk;

    initial begin
        wr_mem = 0;
        adres  = 0;
        dane   = 0;
        #10;




        @(posedge clk);
        wr_mem = 1;
        adres  = 8'd0;
        dane   = 8'hAA;
        @(posedge clk);
        wr_mem = 0;

        @(posedge clk);
        wr_mem = 1;
        adres  = 8'd1;
        dane   = 8'h55;
        @(posedge clk);
        wr_mem = 0;

        @(posedge clk);
        wr_mem = 1;
        adres  = 8'd10;
        dane   = 8'hCC;
        @(posedge clk);
        wr_mem = 0;

        @(posedge clk);
        adres = 8'd0;

        @(posedge clk);
        adres = 8'd1;

        @(posedge clk);
        adres = 8'd10;

        @(posedge clk);
        adres = 8'd2;

        #300;
        $finish;
    end

    initial begin
        $dumpfile("ram_tb.vcd");
        $dumpvars(0, ram_tb);
    end


endmodule

src/tb/ram_tb.vcd
$date
	Tue Dec 16 15:21:37 2025
$end
$version
	Icarus Verilog
$end
$timescale
	1ps
$end
$scope module ram_tb $end
$var wire 16 ! out [15:0] $end
$var parameter 32 " adres_W $end
$var parameter 32 # data_W $end
$var reg 5 $ adres [4:0] $end
$var reg 1 % clk $end
$var reg 16 & dane [15:0] $end
$var reg 1 ' wr_mem $end
$scope module DUT $end
$var wire 5 ( adres [4:0] $end
$var wire 1 % clk $end
$var wire 16 ) data [15:0] $end
$var wire 1 ' wr $end
$var parameter 32 * ADDR_WIDTH $end
$var parameter 32 + DATA_WIDTH $end
$var reg 16 , data_out [15:0] $end
$scope begin Ram $end
$upscope $end
$upscope $end
$upscope $end
$enddefinitions $end
$comment Show the parameter values. $end
$dumpall
b10000 +
b101 *
b10000 #
b101 "
$end
#0
$dumpvars
bx ,
b0 )
b0 (
0'
b0 &
1%
b0 $
bx !
$end
#5000
0%
#10000
b10101010 &
b10101010 )
1'
1%
#15000
0%
#20000
b10101010 !
b10101010 ,
0'
1%
#25000
0%
#30000
bx !
bx ,
b1010101 &
b1010101 )
b1 $
b1 (
1'
1%
#35000
0%
#40000
b1010101 !
b1010101 ,
0'
1%
#45000
0%
#50000
bx !
bx ,
b11001100 &
b11001100 )
b1010 $
b1010 (
1'
1%
#55000
0%
#60000
b11001100 !
b11001100 ,
0'
1%
#65000
0%
#70000
b10101010 !
b10101010 ,
b0 $
b0 (
1%
#75000
0%
#80000
b1010101 !
b1010101 ,
b1 $
b1 (
1%
#85000
0%
#90000
b11001100 !
b11001100 ,
b1010 $
b1010 (
1%
#95000
0%
#100000
bx !
bx ,
b10 $
b10 (
1%
